pycypher-0.5.9.dist-info/DESCRIPTION.rst
pycypher-0.5.9.dist-info/METADATA
pycypher-0.5.9.dist-info/RECORD
pycypher-0.5.9.dist-info/WHEEL
pycypher-0.5.9.dist-info/metadata.json
pycypher-0.5.9.dist-info/top_level.txt
pycypher-0.5.9.data/data/LICENSE
pycypher/node_types.c
pycypher/parser.c
pycypher/version.py
pycypher/decorators.py
pycypher/bindings.c
pycypher/operators.c
pycypher/getters.py
pycypher/bindings.so
pycypher/__init__.py
pycypher/props.c
pycypher/extract_props.c
pycypher/ast.py
pycypher/tests/test_foreach.py
pycypher/tests/test_return.py
pycypher/tests/test_match.py
pycypher/tests/test_constraints.py
pycypher/tests/test_start.py
pycypher/tests/test_delete.py
pycypher/tests/test_statement.py
pycypher/tests/utils.py
pycypher/tests/test_expression.py
pycypher/tests/test_merge.py
pycypher/tests/test_remove.py
pycypher/tests/test_create.py
pycypher/tests/test_with.py
pycypher/tests/test_errors.py
pycypher/tests/test_command.py
pycypher/tests/test_reduce.py
pycypher/tests/test_union.py
pycypher/tests/test_pattern.py
pycypher/tests/test_indexes.py
pycypher/tests/test_invoke_from_thread.py
pycypher/tests/test_map_projection.py
pycypher/tests/test_pattern_comprehension.py
pycypher/tests/__init__.py
pycypher/tests/test_load_csv.py
pycypher/tests/test_cypher_ast_node.py
pycypher/tests/test_call.py
pycypher/tests/test_list_comprehensions.py
pycypher/tests/test_query.py
pycypher/tests/test_case.py
pycypher/tests/test_set.py
pycypher/tests/test_unwind.py
pycypher/.libs/libcypher-parser-9569b30a.so.8.2.0
